<?xml version="1.0" encoding="utf-8"?>
<Defs>
  <ThingCategoryDef>
    <defName>AQTropicalFish</defName>
    <label>Tropical Fish</label>
    <parent>Items</parent>
  </ThingCategoryDef>
  <ThingDef ParentName="ResourceBase" Name="FishInBagBase" Abstract="true">
    <defName>AQFishInBagBase</defName>
    <graphicData>
      <graphicClass>Graphic_Single</graphicClass>
    </graphicData>
    <thingClass>ThingWithComps</thingClass>
    <statBases>
      <MarketValue>30</MarketValue>
      <MaxHitPoints>50</MaxHitPoints>
      <Mass>0.3</Mass>
      <Flammability>0.4</Flammability>
      <DeteriorationRate>0.5</DeteriorationRate>
    </statBases>
    <resourceReadoutPriority>Middle</resourceReadoutPriority>
    <stackLimit>1</stackLimit>
    <thingCategories Inherit="false">
      <li>AQTropicalFish</li>
    </thingCategories>
    <tradeTags>
      <li>ExoticMisc</li>
    </tradeTags>
    <tickerType>Normal</tickerType>
    <comps>
      <li Class="Aquarium.CompProperties_AQFishInBag" />
    </comps>
  </ThingDef>
  <ThingDef ParentName="FishInBagBase">
    <defName>AQFishInBagOne</defName>
    <label>Lionfish</label>
    <description>Pterois is a genus of venomous marine fish, commonly known as lionfish. Also called zebrafish, firefish, turkeyfish, tastyfish or butterfly-cod, it is characterized by conspicuous warning coloration with red, white, creamy, or black bands, showy pectoral fins, and venomous spiky fin rays.</description>
    <graphicData>
      <texPath>Things/Fish/ForSale/FishBag1</texPath>
    </graphicData>
    <statBases>
      <MarketValue>45</MarketValue>
      <Mass>0.3</Mass>
    </statBases>
  </ThingDef>
  <ThingDef ParentName="FishInBagBase">
    <defName>AQFishInBagTwo</defName>
    <label>Goldfish</label>
    <description>The goldfish (Carassius auratus) is a freshwater fish in the family Cyprinidae of order Cypriniformes, a relatively small member of the carp family. It is one of the most commonly kept aquarium fish.</description>
    <graphicData>
      <texPath>Things/Fish/ForSale/FishBag2</texPath>
    </graphicData>
    <statBases>
      <MarketValue>20</MarketValue>
      <Mass>0.1</Mass>
    </statBases>
  </ThingDef>
  <ThingDef ParentName="FishInBagBase">
    <defName>AQFishInBagThree</defName>
    <label>Fighting fish (green)</label>
    <description>The Siamese fighting fish (Betta splendens), also known as the betta, is a popular fish in the aquarium trade. Bettas are a member of the gourami family and are known to be highly territorial.</description>
    <graphicData>
      <texPath>Things/Fish/ForSale/FishBag3</texPath>
    </graphicData>
    <statBases>
      <MarketValue>35</MarketValue>
      <Mass>0.05</Mass>
    </statBases>
  </ThingDef>
  <ThingDef ParentName="FishInBagBase">
    <defName>AQFishInBagFour</defName>
    <label>Fighting fish (red)</label>
    <description>The Siamese fighting fish (Betta splendens), also known as the betta, is a popular fish in the aquarium trade. Bettas are a member of the gourami family and are known to be highly territorial.</description>
    <graphicData>
      <texPath>Things/Fish/ForSale/FishBag4</texPath>
    </graphicData>
    <statBases>
      <MarketValue>30</MarketValue>
      <Mass>0.05</Mass>
    </statBases>
  </ThingDef>
  <ThingDef ParentName="FishInBagBase">
    <defName>AQFishInBagFive</defName>
    <label>Snakeskin barb</label>
    <description>Desmopuntius rhomboocellatus, is a species of cyprinid fish. The specific rhomboocellatus refers to the rhomboid ocellus markings of the flanks, which sometimes gives rise to the common name "Snakeskin barb".</description>
    <graphicData>
      <texPath>Things/Fish/ForSale/FishBag5</texPath>
    </graphicData>
    <statBases>
      <MarketValue>30</MarketValue>
      <Mass>0.1</Mass>
    </statBases>
  </ThingDef>
  <ThingDef ParentName="FishInBagBase">
    <defName>AQFishInBagSix</defName>
    <label>Lemon cichlid</label>
    <description>Neolamprologus leleupi (lemon cichlid) is a species of cichlid endemic to Lake Tanganyika where it occurs throughout the lake. It is a recess-dweller, inhabiting cracks and crevices.</description>
    <graphicData>
      <texPath>Things/Fish/ForSale/FishBag6</texPath>
    </graphicData>
    <statBases>
      <MarketValue>35</MarketValue>
      <Mass>0.07</Mass>
    </statBases>
  </ThingDef>
  <ThingDef ParentName="FishInBagBase">
    <defName>AQFishInBagSeven</defName>
    <label>Fighting fish (blue)</label>
    <description>The Siamese fighting fish (Betta splendens), also known as the betta, is a popular fish in the aquarium trade. Bettas are a member of the gourami family and are known to be highly territorial.</description>
    <graphicData>
      <texPath>Things/Fish/ForSale/FishBag7</texPath>
    </graphicData>
    <statBases>
      <MarketValue>25</MarketValue>
      <Mass>0.05</Mass>
    </statBases>
  </ThingDef>
  <ThingDef ParentName="FishInBagBase">
    <defName>AQFishInBagEight</defName>
    <label>Arowana</label>
    <description>The Asian arowana is a prehistoric freshwater fish that has a long, narrow and flat body. The arowana is often called "dragon fish" because of its enormous scales and long, whisker-like chin barbels.</description>
    <graphicData>
      <texPath>Things/Fish/ForSale/FishBag8</texPath>
    </graphicData>
    <statBases>
      <MarketValue>35</MarketValue>
      <Mass>0.05</Mass>
    </statBases>
  </ThingDef>
  <ThingDef ParentName="FishInBagBase">
    <defName>AQFishInBagNine</defName>
    <label>Cherry Shrimp</label>
    <description>The Cherry Shrimp (Neocaridina heteropoda), also known as Red Cherry Shrimp or RCS, is a dwarf freshwater shrimp native to Taiwan. Suitable for both beginners and experienced aquarists, it is one of the hardiest and easy to keep Shrimp available.</description>
    <graphicData>
      <texPath>Things/Fish/ForSale/FishBag9</texPath>
    </graphicData>
    <statBases>
      <MarketValue>20</MarketValue>
      <Mass>0.05</Mass>
    </statBases>
  </ThingDef>
  <ThingDef ParentName="FishInBagBase">
    <defName>AQFishInBagTen</defName>
    <label>Gourami</label>
    <description>A Gourami is any fish in the Osphronemidae family. These fish are known for their bright colors and unique appearance. People keep many different species in home aquariums.</description>
    <graphicData>
      <texPath>Things/Fish/ForSale/FishBag10</texPath>
    </graphicData>
    <statBases>
      <MarketValue>25</MarketValue>
      <Mass>0.05</Mass>
    </statBases>
  </ThingDef>
  <ThingDef ParentName="FishInBagBase">
    <defName>AQFishInBagEleven</defName>
    <label>Zebra Angelfish</label>
    <description>Zebra angelfish, also known as Zebra lyretail. Zebra angelfish inhabit steep slopes in moderate to deep waters and are found only in the Red Sea and the Western Indian Ocean.</description>
    <graphicData>
      <texPath>Things/Fish/ForSale/FishBag11</texPath>
    </graphicData>
    <statBases>
      <MarketValue>30</MarketValue>
      <Mass>0.05</Mass>
    </statBases>
  </ThingDef>
  <ThingDef ParentName="FishInBagBase">
    <defName>AQFishInBagTwelve</defName>
    <label>Blue Tang</label>
    <description>The Blue Tang boasts a vibrant electric blue body dressed with bold black markings. In fact, the black that begins at the eyes, traces the dorsal line down to the tail, and circles back above the pectoral fin to create a unique shape reminiscent of a painter's palette.</description>
    <graphicData>
      <texPath>Things/Fish/ForSale/FishBag12</texPath>
    </graphicData>
    <statBases>
      <MarketValue>35</MarketValue>
      <Mass>0.05</Mass>
    </statBases>
  </ThingDef>
  <ThingDef ParentName="FishInBagBase">
    <defName>AQFishInBagThirteen</defName>
    <label>Koi</label>
    <description>Koi fish are a colorful, ornamental versions of the common carp. There are now dozens of different color varieties of koi.</description>
    <graphicData>
      <texPath>Things/Fish/ForSale/FishBag13</texPath>
    </graphicData>
    <statBases>
      <MarketValue>45</MarketValue>
      <Mass>0.05</Mass>
    </statBases>
  </ThingDef>
  <ThingDef ParentName="FishInBagBase">
    <defName>AQFishInBagFourteen</defName>
    <label>Clownfish</label>
    <description>Bright orange with three distinctive white bars, clown anemonefish are among the most recognizable of all reef-dwellers. They reach about 4.3 inches in length, and are named for the multicolored sea anemone in which they make their homes.</description>
    <graphicData>
      <texPath>Things/Fish/ForSale/FishBag14</texPath>
    </graphicData>
    <statBases>
      <MarketValue>40</MarketValue>
      <Mass>0.05</Mass>
    </statBases>
  </ThingDef>
  <ThingDef ParentName="FishInBagBase">
    <defName>AQFishInBagFifteen</defName>
    <label>Axolotl</label>
    <description>The axolotl salamander has the rare trait of retaining its larval features throughout its adult life. Axolotls are long-lived, surviving up to 15 years on a diet of mollusks, worms, insect larvae, crustaceans, and some fish.</description>
    <graphicData>
      <texPath>Things/Fish/ForSale/FishBag15</texPath>
    </graphicData>
    <statBases>
      <MarketValue>65</MarketValue>
      <Mass>0.05</Mass>
    </statBases>
  </ThingDef>
  <ThingDef ParentName="FishInBagBase">
    <defName>AQFishInBagSixteen</defName>
    <label>Cerulean Angelfish</label>
    <description>Possibly the most recognized freshwater fish in the aquarium hobby, angelfish belong to the family Cichlidae. Admired for their graceful swimming behavior, angelfish make stunning additions to large community aquariums.</description>
    <graphicData>
      <texPath>Things/Fish/ForSale/FishBag16</texPath>
    </graphicData>
    <statBases>
      <MarketValue>30</MarketValue>
      <Mass>0.05</Mass>
    </statBases>
  </ThingDef>
  <ThingDef ParentName="FishInBagBase">
    <defName>AQFishInBagSeventeen</defName>
    <label>Plecostomus</label>
    <description>Plecos are well-known algae eaters that originated in the rivers of the Amazon jungle in South America. Plecos attach themselves to hard surfaces with specially adapted mouth parts.</description>
    <graphicData>
      <texPath>Things/Fish/ForSale/FishBag17</texPath>
    </graphicData>
    <statBases>
      <MarketValue>55</MarketValue>
      <Mass>0.05</Mass>
    </statBases>
  </ThingDef>
</Defs>